<?xml version="1.0" encoding="UTF-8"?>
<?xml-stylesheet type="text/css" href="p5b.css"?>
<STUDENTDATA>
<STUDENT>
<USN>USN : 2SA20CS010</USN>
<NAME>NAME : JABIRHUSSIAN</NAME>
<COLLEGE>COLLEGE : SIET</COLLEGE>
<BRANCH>BRANCH :CSE</BRANCH>
<YEAR>YEAR : 2023</YEAR>
<EMAIL>E-MAIL : jab@gmail.com</EMAIL>
</STUDENT>
<STUDENT>
<USN>USN : 2SA20CS032</USN>
<NAME>NAME : SAMEER BASHA</NAME>
<COLLEGE>COLLEGE : SIET</COLLEGE>
<BRANCH>BRANCH :CSE</BRANCH>
<YEAR>YEAR : 2023</YEAR>
<EMAIL>E-MAIL : sameer@gmail.com</EMAIL>
</STUDENT>
<STUDENT>
<USN>USN : 2SA20CS020</USN>
<NAME>NAME : NASIR (Z)(LAL)</NAME>
<COLLEGE>COLLEGE : SIET</COLLEGE>
<BRANCH>BRANCH :CSE</BRANCH>
<YEAR>YEAR : 2023</YEAR>
<EMAIL>E-MAIL : lalnasirz@gmail.com</EMAIL>
</STUDENT>
</STUDENTDATA>
